geoarchive/__init__.py
geoarchive/zotero.py
geoarchive-0.1.4.dist-info/LICENSE
geoarchive-0.1.4.dist-info/WHEEL
geoarchive-0.1.4.dist-info/METADATA
geoarchive-0.1.4.dist-info/RECORD
